[{
  "_id": 1,
  "name": "MotionDetetcion",
  "title": "Motion detection",
  "icon": "fa fa-video",
  "is_group": false,
  "parent": null,
  "view": "MotionDetetcion",
  "is_deleted": false,
  "modified": "2024/01/01 12:00"
},
{
  "_id": 2,
  "name": "Masters",
  "title": "Masters",
  "icon": "fa fa-user",
  "is_group": true,
  "parent": null,
  "view": "",
  "is_deleted": false,
  "modified": "2024/01/01 12:00"
},
{
  "_id": 3,
  "name": "Units",
  "title": "Manage Units",
  "icon": "fa fa-user",
  "is_group": false,
  "parent": 2,
  "view": "units",
  "is_deleted": false,
  "modified": "2024/01/01 12:00"
},
{
  "_id": 4,
  "name": "Menus",
  "title": "Manage Menus",
  "icon": "fa fa-user",
  "is_group": false,
  "parent": 2,
  "is_deleted": false,
  "modified": "2024/01/01 12:00",
  "view": "menus"
},
{
  "_id": 5,
  "name": "Users",
  "title": "Manage Users",
  "icon": "fa fa-user",
  "is_group": false,
  "parent": 2,
  "view": "users",
  "is_deleted": false,
  "modified": "2024/01/01 12:00"
},
{
  "_id": 6,
  "name": "Settings",
  "title": "Manage Settings",
  "icon": "fa fa-user",
  "is_group": false,
  "parent": 2,
  "view": "settings",
  "is_deleted": false,
  "modified": "2024/01/01 12:00"
},
{
  "_id": 7,
  "name": "TextExtraction ",
  "title": "Text extraction ",
  "icon": "fa fa-file-alt",
  "is_group": false,
  "parent": null,
  "view": "TextExtraction ",
  "is_deleted": false,
  "modified": "2024/01/01 12:00"
},
{
  "_id": 8,
  "name": "ImageBlurring",
  "title": "Image Blurring",
  "icon": "fa fa-tint",
  "is_group": false,
  "parent": null,
  "view": "blur_module",
  "is_deleted": false,
  "modified": "2024/01/01 12:00"
},
{
  "_id": 9,
  "name": "ObjectDetection",
  "title": "Object Detection",
  "icon": "fa fa-bullseye",
  "is_group": false,
  "parent": null,
  "view": "Object Detection",
  "is_deleted": false,
  "modified": "2024/01/01 12:00"
},
{
  "_id": 10,
  "name": "FaceRecognition",
  "title": "Face Recognition",
  "icon": "fa fa-user-circle",
  "is_group": false,
  "parent": null,
  "view": "Face Recognition",
  "is_deleted": false,
  "modified": "2024/01/01 12:00"
},
{
  "_id": 11,
  "name": "ImageSegmentation",
  "title": "Image Segmentation",
  "icon": "fa fa-th-large",
  "is_group": false,
  "parent": null,
  "view": "Image Segmentation",
  "is_deleted": false,
  "modified": "2024/01/01 12:00"
},
{
  "_id": 12,
  "name": "AnomalyDetection",
  "title": "Anomaly Detection",
  "icon": "fa fa-exclamation-circle",
  "is_group": false,
  "parent": null,
  "view": "Anomaly Detection",
  "is_deleted": false,
  "modified": "2024/01/01 12:00"
},
{
  "_id": 13,
  "name": "ImageEnhancement",
  "title": "Image Enhancement",
  "icon": "fa fa-magic",
  "is_group": false,
  "parent": null,
  "view": "Image Enhancement",
  "is_deleted": false,
  "modified": "2024/01/01 12:00"
},
{
  "_id": 14,
  "name": "PoseEstimation",
  "title": "Pose Estimation",
  "icon": "fa fa-walking",
  "is_group": false,
  "parent": null,
  "view": "Pose Estimation",
  "is_deleted": false,
  "modified": "2024/01/01 12:00"
}]